pybuilder_git_version/__init__.py
pybuilder_git_version/util.py
pybuilder_git_version-0.6.0.dist-info/METADATA
pybuilder_git_version-0.6.0.dist-info/WHEEL
pybuilder_git_version-0.6.0.dist-info/namespace_packages.txt
pybuilder_git_version-0.6.0.dist-info/top_level.txt
pybuilder_git_version-0.6.0.dist-info/zip-safe
pybuilder_git_version-0.6.0.dist-info/RECORD
