Metadata-Version: 2.1
Name: pybuilder-git-version
Version: 0.6.0
Summary: A Git versioning plugin for PyBuilder
Home-page: https://github.com/jlsheehan/pybuilder-git-version
Author: Jeffrey Sheehan
Author-email: jeff.sheehan7@gmail.com
Maintainer: 
Maintainer-email: 
License: MIT License
Classifier: Development Status :: 3 - Alpha
Classifier: Programming Language :: Python
Requires-Dist: gitpython (==3.1.43)
Requires-Dist: semver (==2.13.0)
